README.md
setup.cfg
setup.py
huskarl/__init__.py
huskarl/core.py
huskarl/memory.py
huskarl/policy.py
huskarl/simulation.py
huskarl/agent/__init__.py
huskarl/agent/a2c.py
huskarl/agent/ddpg.py
huskarl/agent/dqn.py
huskarl_custom.egg-info/PKG-INFO
huskarl_custom.egg-info/SOURCES.txt
huskarl_custom.egg-info/dependency_links.txt
huskarl_custom.egg-info/requires.txt
huskarl_custom.egg-info/top_level.txt