Metadata-Version: 1.2
Name: huskarl-custom
Version: 0.4
Summary: Deep Reinforcement Learning Framework
Home-page: https://github.com/danaugrs/huskarl
Author: Daniel Salvadori
Author-email: danaugrs@gmail.com
License: UNKNOWN
Platform: UNKNOWN
Classifier: Development Status :: 3 - Alpha
Classifier: Intended Audience :: Developers
Classifier: Topic :: Scientific/Engineering :: Artificial Intelligence
Classifier: License :: OSI Approved :: MIT License
Classifier: Programming Language :: Python :: 3
Requires-Python: >=3.6
